{
"type": "FeatureCollection",
"name": "utility_outages",
"crs": { "type": "name", "properties": { "name": "urn:ogc:def:crs:OGC:1.3:CRS84" } },
"features": [
{ "type": "Feature", "properties": { "outage_id": 101, "priority_level": "High", "affected_customers": 420 }, "geometry": { "type": "Point", "coordinates": [ -77.09, 38.95 ] } },
{ "type": "Feature", "properties": { "outage_id": 102, "priority_level": "Medium", "affected_customers": 180 }, "geometry": { "type": "Point", "coordinates": [ -77.04, 38.92 ] } },
{ "type": "Feature", "properties": { "outage_id": 103, "priority_level": "High", "affected_customers": 350 }, "geometry": { "type": "Point", "coordinates": [ -77.01, 38.885 ] } },
{ "type": "Feature", "properties": { "outage_id": 104, "priority_level": "Low", "affected_customers": 75 }, "geometry": { "type": "Point", "coordinates": [ -76.98, 38.86 ] } },
{ "type": "Feature", "properties": { "outage_id": 105, "priority_level": "Medium", "affected_customers": 210 }, "geometry": { "type": "Point", "coordinates": [ -76.97, 38.88 ] } }
]
}
